setup.py
scirocco_pyclient.egg-info/PKG-INFO
scirocco_pyclient.egg-info/SOURCES.txt
scirocco_pyclient.egg-info/dependency_links.txt
scirocco_pyclient.egg-info/requires.txt
scirocco_pyclient.egg-info/top_level.txt
sciroccoclient/__init__.py
sciroccoclient/client.py
sciroccoclient/clientfactory.py
sciroccoclient/exceptions.py
sciroccoclient/httpclient.py
sciroccoclient/responses.py
sciroccoclient/systemdata.py
sciroccoclient/http/__init__.py
sciroccoclient/http/base.py
sciroccoclient/http/messagedao.py
sciroccoclient/http/messagequeuedao.py
sciroccoclient/http/requestadapter.py