Metadata-Version: 1.1
Name: scirocco-pyclient
Version: v1.0.0
Summary: Client library for scirocco proyect.
Home-page: https://github.com/eloylp/scirocco-pyclient
Author: eloylp
Author-email: eloy@sandboxwebs.com
License: GNU AFFERO 3
Download-URL: https://github.com/eloylp/scirocco-pyclient/tarball/v1.0.0
Platform: any
Classifier: Programming Language :: Python :: 3 :: Only
Classifier: Development Status :: 4 - Beta
Classifier: Natural Language :: English
Classifier: Environment :: Console
Classifier: Intended Audience :: Developers
Classifier: Intended Audience :: System Administrators
Classifier: Topic :: Internet :: WWW/HTTP
Classifier: Topic :: Software Development :: Embedded Systems
Classifier: Topic :: System :: Networking :: Monitoring
Classifier: License :: Freely Distributable
Classifier: Operating System :: POSIX :: Linux
